{"ongoing_trials": {"tuner0": "02"}, "hyperparameters": {"space": [{"class_name": "Choice", "config": {"name": "activationfunc", "default": "relu", "conditions": [], "values": ["relu", "tanh", "selu"], "ordered": false}}, {"class_name": "Choice", "config": {"name": "dropout", "default": 0.05, "conditions": [], "values": [0.05, 0.1, 0.2], "ordered": true}}, {"class_name": "Int", "config": {"name": "first_layer_neurons", "default": null, "conditions": [], "min_value": 32, "max_value": 512, "step": 32, "sampling": null}}, {"class_name": "Int", "config": {"name": "n_layers", "default": null, "conditions": [], "min_value": 1, "max_value": 4, "step": 1, "sampling": null}}, {"class_name": "Int", "config": {"name": "lstm_0_units", "default": null, "conditions": [], "min_value": 32, "max_value": 512, "step": 32, "sampling": null}}, {"class_name": "Int", "config": {"name": "second_layer_neurons", "default": null, "conditions": [], "min_value": 32, "max_value": 512, "step": 32, "sampling": null}}, {"class_name": "Choice", "config": {"name": "learning_rate", "default": 0.01, "conditions": [], "values": [0.01, 0.001, 0.0001], "ordered": true}}, {"class_name": "Int", "config": {"name": "lstm_1_units", "default": null, "conditions": [], "min_value": 32, "max_value": 512, "step": 32, "sampling": null}}, {"class_name": "Int", "config": {"name": "lstm_2_units", "default": null, "conditions": [], "min_value": 32, "max_value": 512, "step": 32, "sampling": null}}], "values": {"activationfunc": "relu", "dropout": 0.05, "first_layer_neurons": 32, "n_layers": 1, "lstm_0_units": 32, "second_layer_neurons": 32, "learning_rate": 0.01, "lstm_1_units": 32, "lstm_2_units": 32}}, "seed": 45, "seed_state": 70, "tried_so_far": ["3faba022333dcab26a2f481ace26b36d", "4f73eb5445f5aa64a4a38334381aa433", "fc2675426dee79c030e17d7a4714a8f6"]}